{
  "GLD": {
    "score": -3,
    "signal": "SELL",
    "price": 365.9200134277344,
    "fund_score": 1.6,
    "comp_score": 1.84,
    "fund": {
      "pe": null,
      "pbv": 2.1522555,
      "roe": null,
      "div_yld": 0.0,
      "has_div": false,
      "ex_div_date": null,
      "de_ratio": null,
      "eps_growth": null,
      "fcf_yield": null,
      "avg_volume": 7835251
    },
    "vol_20d": 0.017893520024802642,
    "avg_volume": 7857480.0,
    "buy_alerted": false,
    "sell_alerted": false,
    "fund_fetched": null
  },
  "SCB.BK": {
    "score": 4,
    "signal": "STRONG BUY",
    "price": 143.5,
    "fund_score": 5.3,
    "comp_score": 7.52,
    "fund": {
      "pe": 10.70097,
      "pbv": 0.9635917,
      "roe": 0.090579994,
      "div_yld": 7.89,
      "has_div": true,
      "ex_div_date": "2026-04-20",
      "de_ratio": null,
      "eps_growth": -0.183,
      "fcf_yield": null,
      "avg_volume": 18970261
    },
    "vol_20d": 0.011200723104495006,
    "avg_volume": 18203706.4,
    "buy_alerted": false,
    "sell_alerted": false,
    "fund_fetched": "2026-06-22"
  },
  "TRUE.BK": {
    "score": -2,
    "signal": "SELL",
    "price": 12.5,
    "fund_score": 5.3,
    "comp_score": 3.92,
    "fund": {
      "pe": 30.487804,
      "pbv": 5.720824,
      "roe": 0.17861,
      "div_yld": 3.36,
      "has_div": true,
      "ex_div_date": "2026-05-20",
      "de_ratio": 5.2253300000000005,
      "eps_growth": 2.8,
      "fcf_yield": 0.06525808708721467,
      "avg_volume": 164111661
    },
    "vol_20d": 0.008084268322395944,
    "avg_volume": 122348190.85,
    "buy_alerted": false,
    "sell_alerted": false,
    "fund_fetched": "2026-05-08"
  },
  "PTT.BK": {
    "score": -2,
    "signal": "SELL",
    "price": 34.5,
    "fund_score": 6.8,
    "comp_score": 4.52,
    "fund": {
      "pe": 10.615385,
      "pbv": 0.8321474,
      "roe": 0.07466,
      "div_yld": 6.0,
      "has_div": true,
      "ex_div_date": "2026-03-05",
      "de_ratio": 0.60587,
      "eps_growth": 0.117,
      "fcf_yield": 0.0800985012135556,
      "avg_volume": 73326977
    },
    "vol_20d": 0.008680245127386483,
    "avg_volume": 47343692.25,
    "buy_alerted": false,
    "sell_alerted": false,
    "fund_fetched": "2026-05-08"
  },
  "CPALL.BK": {
    "score": 0,
    "signal": "HOLD",
    "price": 45.0,
    "fund_score": 5.8,
    "comp_score": 5.32,
    "fund": {
      "pe": 13.719512,
      "pbv": 2.9000452,
      "roe": 0.09954,
      "div_yld": 3.61,
      "has_div": true,
      "ex_div_date": "2026-04-30",
      "de_ratio": 1.25856,
      "eps_growth": 0.215,
      "fcf_yield": 0.07068888362729912,
      "avg_volume": 32768987
    },
    "vol_20d": 0.010961372059499971,
    "avg_volume": 27966153.45,
    "buy_alerted": false,
    "sell_alerted": false,
    "fund_fetched": "2026-06-19"
  },
  "DELTA.BK": {
    "score": -1,
    "signal": "WATCH",
    "price": 326.0,
    "fund_score": 5.8,
    "comp_score": 4.72,
    "fund": {
      "pe": 142.35808,
      "pbv": 38.177776,
      "roe": 0.29577,
      "div_yld": 0.19,
      "has_div": true,
      "ex_div_date": "2026-02-26",
      "de_ratio": 0.013859999999999999,
      "eps_growth": 0.659,
      "fcf_yield": 0.0006450193232186475,
      "avg_volume": 16880084
    },
    "vol_20d": 0.027855008091210855,
    "avg_volume": 15409840.5,
    "buy_alerted": false,
    "sell_alerted": false,
    "fund_fetched": "2026-06-04"
  },
  "KBANK.BK": {
    "score": 2,
    "signal": "BUY",
    "price": 212.0,
    "fund_score": 5.8,
    "comp_score": 6.52,
    "fund": {
      "pe": 10.0,
      "pbv": 0.8492025,
      "roe": 0.085310005,
      "div_yld": 5.77,
      "has_div": true,
      "ex_div_date": "2026-04-21",
      "de_ratio": null,
      "eps_growth": 0.1,
      "fcf_yield": null,
      "avg_volume": 17403954
    },
    "vol_20d": 0.010439033482518163,
    "avg_volume": 15210446.65,
    "buy_alerted": false,
    "sell_alerted": false,
    "fund_fetched": "2026-06-22"
  },
  "BH.BK": {
    "score": 3,
    "signal": "BUY",
    "price": 186.0,
    "fund_score": 5.3,
    "comp_score": 6.92,
    "fund": {
      "pe": 21.502892,
      "pbv": 4.52753,
      "roe": 0.24379,
      "div_yld": 2.71,
      "has_div": true,
      "ex_div_date": "2026-03-17",
      "de_ratio": 0.00314,
      "eps_growth": 0.03,
      "fcf_yield": 0.021487959921169114,
      "avg_volume": 4983980
    },
    "vol_20d": 0.016224060414644272,
    "avg_volume": 4882203.2,
    "buy_alerted": false,
    "sell_alerted": false,
    "fund_fetched": "2026-06-22"
  },
  "ADVANC.BK": {
    "score": 0,
    "signal": "HOLD",
    "price": 353.0,
    "fund_score": 4.7,
    "comp_score": 4.88,
    "fund": {
      "pe": 20.655354,
      "pbv": 8.714113,
      "roe": 0.48064998,
      "div_yld": 4.76,
      "has_div": true,
      "ex_div_date": "2026-02-27",
      "de_ratio": 1.8321399999999999,
      "eps_growth": 0.275,
      "fcf_yield": 0.02932864335721868,
      "avg_volume": 7592712
    },
    "vol_20d": 0.011088153831271581,
    "avg_volume": 6468130.0,
    "buy_alerted": false,
    "sell_alerted": false,
    "fund_fetched": "2026-06-16"
  },
  "GULF.BK": {
    "score": 1,
    "signal": "WATCH",
    "price": 60.5,
    "fund_score": 5.3,
    "comp_score": 5.72,
    "fund": {
      "pe": 35.588234,
      "pbv": 2.609333,
      "roe": 0.36189997,
      "div_yld": 1.71,
      "has_div": true,
      "ex_div_date": "2026-03-02",
      "de_ratio": 1.0662399999999999,
      "eps_growth": 0.327,
      "fcf_yield": -0.02126645188101462,
      "avg_volume": 60677000
    },
    "vol_20d": 0.01975054454862347,
    "avg_volume": 64421459.0,
    "buy_alerted": false,
    "sell_alerted": false,
    "fund_fetched": "2026-06-08"
  },
  "BBL.BK": {
    "score": 4,
    "signal": "STRONG BUY",
    "price": 175.5,
    "fund_score": 5.3,
    "comp_score": 7.52,
    "fund": {
      "pe": 7.548387,
      "pbv": 0.579669,
      "roe": 0.07818,
      "div_yld": 9.35,
      "has_div": true,
      "ex_div_date": "2026-04-22",
      "de_ratio": null,
      "eps_growth": -0.129,
      "fcf_yield": null,
      "avg_volume": 10235801
    },
    "vol_20d": 0.013386919889823126,
    "avg_volume": 11626925.85,
    "buy_alerted": false,
    "sell_alerted": false,
    "fund_fetched": "2026-06-22"
  },
  "MINT.BK": {
    "score": 2,
    "signal": "BUY",
    "price": 24.799999237060547,
    "fund_score": 4.2,
    "comp_score": 5.88,
    "fund": {
      "pe": 18.507462,
      "pbv": 2.3592083,
      "roe": 0.10196,
      "div_yld": 2.86,
      "has_div": true,
      "ex_div_date": "2026-05-05",
      "de_ratio": 1.90285,
      "eps_growth": null,
      "fcf_yield": 0.12948487213640036,
      "avg_volume": 34954589
    },
    "vol_20d": 0.02430440261410225,
    "avg_volume": 40698675.7,
    "buy_alerted": false,
    "sell_alerted": false,
    "fund_fetched": "2026-06-22"
  },
  "IVL.BK": {
    "score": -2,
    "signal": "SELL",
    "price": 21.0,
    "fund_score": 4.2,
    "comp_score": 3.48,
    "fund": {
      "pe": 16.826923,
      "pbv": 1.0805805,
      "roe": -0.05899,
      "div_yld": 3.33,
      "has_div": true,
      "ex_div_date": "2026-05-28",
      "de_ratio": 2.00097,
      "eps_growth": null,
      "fcf_yield": 0.14299715732333165,
      "avg_volume": 28542135
    },
    "vol_20d": 0.018643196695435866,
    "avg_volume": 17541260.45,
    "buy_alerted": false,
    "sell_alerted": false,
    "fund_fetched": null
  },
  "PTTGC.BK": {
    "score": -3,
    "signal": "SELL",
    "price": 31.5,
    "fund_score": 5.8,
    "comp_score": 3.52,
    "fund": {
      "pe": 14.2757435,
      "pbv": 0.47859976,
      "roe": -0.036760002,
      "div_yld": 1.56,
      "has_div": true,
      "ex_div_date": "2026-02-24",
      "de_ratio": 0.6051,
      "eps_growth": null,
      "fcf_yield": 0.32157481929049264,
      "avg_volume": 29844942
    },
    "vol_20d": 0.025356606592802124,
    "avg_volume": 25092656.45,
    "buy_alerted": false,
    "sell_alerted": false,
    "fund_fetched": null
  },
  "PTTEP.BK": {
    "score": -2,
    "signal": "SELL",
    "price": 129.5,
    "fund_score": 6.3,
    "comp_score": 4.32,
    "fund": {
      "pe": 9.256612,
      "pbv": 0.95807815,
      "roe": 0.10782,
      "div_yld": 6.68,
      "has_div": true,
      "ex_div_date": "2026-02-23",
      "de_ratio": 0.243,
      "eps_growth": -0.229,
      "fcf_yield": 0.000758205259515496,
      "avg_volume": 18751845
    },
    "vol_20d": 0.014302238007437745,
    "avg_volume": 15402124.15,
    "buy_alerted": false,
    "sell_alerted": false,
    "fund_fetched": null
  },
  "TOP.BK": {
    "score": -2,
    "signal": "SELL",
    "price": 44.75,
    "fund_score": 8.9,
    "comp_score": 5.36,
    "fund": {
      "pe": 3.2451053,
      "pbv": 0.5140901,
      "roe": 0.1545,
      "div_yld": 4.49,
      "has_div": true,
      "ex_div_date": "2026-02-25",
      "de_ratio": 0.50307,
      "eps_growth": 4.56,
      "fcf_yield": 0.48210319656691075,
      "avg_volume": 14907119
    },
    "vol_20d": 0.012329074386749446,
    "avg_volume": 9389502.1,
    "buy_alerted": false,
    "sell_alerted": false,
    "fund_fetched": null
  },
  "IRPC.BK": {
    "score": -2,
    "signal": "SELL",
    "price": 1.6799999475479126,
    "fund_score": 6.8,
    "comp_score": 4.52,
    "fund": {
      "pe": 6.0,
      "pbv": 0.46473026,
      "roe": 0.07698,
      "div_yld": 0.61,
      "has_div": true,
      "ex_div_date": "2026-03-02",
      "de_ratio": 0.92015,
      "eps_growth": null,
      "fcf_yield": 0.8763219131409826,
      "avg_volume": 192815515
    },
    "vol_20d": 0.020984233899446664,
    "avg_volume": 102943210.0,
    "buy_alerted": false,
    "sell_alerted": false,
    "fund_fetched": "2026-05-08"
  },
  "RATCH.BK": {
    "score": 2,
    "signal": "BUY",
    "price": 30.5,
    "fund_score": 5.8,
    "comp_score": 6.52,
    "fund": {
      "pe": 10.664336,
      "pbv": 0.6682442,
      "roe": 0.06439,
      "div_yld": 5.29,
      "has_div": true,
      "ex_div_date": "2026-03-12",
      "de_ratio": 0.96465,
      "eps_growth": 0.007,
      "fcf_yield": -0.06502709765981408,
      "avg_volume": 2922317
    },
    "vol_20d": 0.010161234409624506,
    "avg_volume": 2876709.9,
    "buy_alerted": false,
    "sell_alerted": false,
    "fund_fetched": "2026-06-22"
  },
  "BANPU.BK": {
    "score": -2,
    "signal": "SELL",
    "price": 5.199999809265137,
    "fund_score": 4.7,
    "comp_score": 3.68,
    "fund": {
      "pe": 8.843086,
      "pbv": 0.4305344,
      "roe": 0.01569,
      "div_yld": 6.86,
      "has_div": true,
      "ex_div_date": "2026-04-16",
      "de_ratio": 1.4953999999999998,
      "eps_growth": null,
      "fcf_yield": -0.00350308746848296,
      "avg_volume": 46031119
    },
    "vol_20d": 0.012478770256895085,
    "avg_volume": 29458886.5,
    "buy_alerted": false,
    "sell_alerted": false,
    "fund_fetched": "2026-06-02"
  },
  "BPP.BK": {
    "score": -3,
    "signal": "SELL",
    "price": 10.899999618530273,
    "fund_score": 8.4,
    "comp_score": 4.56,
    "fund": {
      "pe": 3.9926739,
      "pbv": 0.59110624,
      "roe": 0.16680999,
      "div_yld": 6.42,
      "has_div": true,
      "ex_div_date": "2026-04-16",
      "de_ratio": 0.39116999999999996,
      "eps_growth": 9.233,
      "fcf_yield": -0.009752045702080601,
      "avg_volume": 151991
    },
    "vol_20d": 0.014145271479005829,
    "avg_volume": 115518.6,
    "buy_alerted": false,
    "sell_alerted": false,
    "fund_fetched": "2026-06-04"
  },
  "GPSC.BK": {
    "score": 3,
    "signal": "BUY",
    "price": 44.5,
    "fund_score": 5.8,
    "comp_score": 7.12,
    "fund": {
      "pe": 17.943548,
      "pbv": 1.1817507,
      "roe": 0.06321,
      "div_yld": 4.37,
      "has_div": true,
      "ex_div_date": "2026-02-25",
      "de_ratio": 0.9464,
      "eps_growth": 0.525,
      "fcf_yield": 0.1153849179618067,
      "avg_volume": 9621092
    },
    "vol_20d": 0.01738227643056233,
    "avg_volume": 7995811.6,
    "buy_alerted": false,
    "sell_alerted": false,
    "fund_fetched": "2026-06-22"
  },
  "BGRIM.BK": {
    "score": 2,
    "signal": "BUY",
    "price": 17.299999237060547,
    "fund_score": 4.7,
    "comp_score": 6.08,
    "fund": {
      "pe": 54.0625,
      "pbv": 2.3957899,
      "roe": 0.062319998,
      "div_yld": 2.41,
      "has_div": true,
      "ex_div_date": "2026-03-10",
      "de_ratio": 2.47389,
      "eps_growth": 0.188,
      "fcf_yield": 0.1529442047055071,
      "avg_volume": 22611285
    },
    "vol_20d": 0.03401272881332482,
    "avg_volume": 27087340.65,
    "buy_alerted": false,
    "sell_alerted": false,
    "fund_fetched": "2026-06-22"
  },
  "EGCO.BK": {
    "score": 1,
    "signal": "WATCH",
    "price": 117.5,
    "fund_score": 3.7,
    "comp_score": 5.08,
    "fund": {
      "pe": 30.519482,
      "pbv": 0.6052552,
      "roe": 0.01921,
      "div_yld": 5.6,
      "has_div": true,
      "ex_div_date": "2026-03-13",
      "de_ratio": 1.00989,
      "eps_growth": -0.756,
      "fcf_yield": -0.05626098331727634,
      "avg_volume": 951192
    },
    "vol_20d": 0.012472466117757802,
    "avg_volume": 1071156.65,
    "buy_alerted": false,
    "sell_alerted": false,
    "fund_fetched": "2026-06-17"
  },
  "GLOBAL.BK": {
    "score": -2,
    "signal": "SELL",
    "price": 6.699999809265137,
    "fund_score": 6.8,
    "comp_score": 4.52,
    "fund": {
      "pe": 19.142857,
      "pbv": 1.4393125,
      "roe": 0.08177,
      "div_yld": 2.85,
      "has_div": true,
      "ex_div_date": "2026-02-24",
      "de_ratio": 0.3031,
      "eps_growth": 0.291,
      "fcf_yield": 0.06568174367601759,
      "avg_volume": 17136947
    },
    "vol_20d": 0.025436383677818118,
    "avg_volume": 17223514.3,
    "buy_alerted": false,
    "sell_alerted": false,
    "fund_fetched": "2026-06-03"
  },
  "HMPRO.BK": {
    "score": 1,
    "signal": "WATCH",
    "price": 6.400000095367432,
    "fund_score": 4.7,
    "comp_score": 5.48,
    "fund": {
      "pe": 14.545455,
      "pbv": 3.023146,
      "roe": 0.20406,
      "div_yld": 7.04,
      "has_div": true,
      "ex_div_date": "2026-04-22",
      "de_ratio": 0.85517,
      "eps_growth": -0.166,
      "fcf_yield": 0.029285540081640974,
      "avg_volume": 31058370
    },
    "vol_20d": 0.013416362610623721,
    "avg_volume": 28473916.7,
    "buy_alerted": false,
    "sell_alerted": false,
    "fund_fetched": "2026-06-17"
  },
  "CRC.BK": {
    "score": 2,
    "signal": "BUY",
    "price": 23.299999237060547,
    "fund_score": 4.7,
    "comp_score": 6.08,
    "fund": {
      "pe": 19.91453,
      "pbv": 2.0112214,
      "roe": 0.099630006,
      "div_yld": 2.27,
      "has_div": true,
      "ex_div_date": "2026-04-21",
      "de_ratio": 1.49452,
      "eps_growth": 0.179,
      "fcf_yield": 0.05573090706907005,
      "avg_volume": 16208147
    },
    "vol_20d": 0.016655665924050995,
    "avg_volume": 13433218.75,
    "buy_alerted": false,
    "sell_alerted": false,
    "fund_fetched": "2026-06-22"
  },
  "COM7.BK": {
    "score": 2,
    "signal": "BUY",
    "price": 28.0,
    "fund_score": 5.8,
    "comp_score": 6.52,
    "fund": {
      "pe": 15.469614,
      "pbv": 5.4591537,
      "roe": 0.39321998,
      "div_yld": 3.89,
      "has_div": true,
      "ex_div_date": "2026-03-10",
      "de_ratio": 0.86714,
      "eps_growth": 0.249,
      "fcf_yield": 0.035569016153172144,
      "avg_volume": 17162589
    },
    "vol_20d": 0.017907820983321113,
    "avg_volume": 11300450.2,
    "buy_alerted": false,
    "sell_alerted": false,
    "fund_fetched": "2026-06-22"
  },
  "OSP.BK": {
    "score": 3,
    "signal": "BUY",
    "price": 17.700000762939453,
    "fund_score": 6.3,
    "comp_score": 7.32,
    "fund": {
      "pe": 14.873949,
      "pbv": 3.1914895,
      "roe": 0.21815,
      "div_yld": 4.57,
      "has_div": true,
      "ex_div_date": "2026-05-07",
      "de_ratio": 0.027309999999999997,
      "eps_growth": -0.086,
      "fcf_yield": 0.10203488278031124,
      "avg_volume": 10947024
    },
    "vol_20d": 0.010167379175589521,
    "avg_volume": 8557676.2,
    "buy_alerted": false,
    "sell_alerted": false,
    "fund_fetched": "2026-06-22"
  },
  "BJC.BK": {
    "score": 0,
    "signal": "HOLD",
    "price": 14.100000381469727,
    "fund_score": 5.3,
    "comp_score": 5.12,
    "fund": {
      "pe": 14.242425,
      "pbv": 0.4630846,
      "roe": 0.03821,
      "div_yld": 3.62,
      "has_div": true,
      "ex_div_date": "2026-04-29",
      "de_ratio": 1.24173,
      "eps_growth": -0.037,
      "fcf_yield": 0.23525556104572717,
      "avg_volume": 4557612
    },
    "vol_20d": 0.007877781458352797,
    "avg_volume": 3471954.6,
    "buy_alerted": false,
    "sell_alerted": false,
    "fund_fetched": "2026-06-17"
  },
  "TU.BK": {
    "score": 0,
    "signal": "HOLD",
    "price": 11.600000381469727,
    "fund_score": 5.8,
    "comp_score": 5.32,
    "fund": {
      "pe": 9.586777,
      "pbv": 1.000345,
      "roe": 0.105579995,
      "div_yld": 6.03,
      "has_div": true,
      "ex_div_date": "2026-03-02",
      "de_ratio": 1.4327,
      "eps_growth": 0.18,
      "fcf_yield": -0.004387768231876799,
      "avg_volume": 9418678
    },
    "vol_20d": 0.010586158854430988,
    "avg_volume": 7916360.15,
    "buy_alerted": false,
    "sell_alerted": false,
    "fund_fetched": "2026-05-08"
  },
  "CBG.BK": {
    "score": 1,
    "signal": "WATCH",
    "price": 44.75,
    "fund_score": 4.7,
    "comp_score": 5.48,
    "fund": {
      "pe": 20.62212,
      "pbv": 3.0353389,
      "roe": 0.14839,
      "div_yld": 2.74,
      "has_div": true,
      "ex_div_date": "2026-03-05",
      "de_ratio": 0.18322,
      "eps_growth": -0.196,
      "fcf_yield": 0.0450057466422182,
      "avg_volume": 4249833
    },
    "vol_20d": 0.01581665308486899,
    "avg_volume": 3795233.3,
    "buy_alerted": false,
    "sell_alerted": false,
    "fund_fetched": "2026-06-04"
  },
  "GFPT.BK": {
    "score": 1,
    "signal": "WATCH",
    "price": 8.949999809265137,
    "fund_score": 7.9,
    "comp_score": 6.76,
    "fund": {
      "pe": 4.8378377,
      "pbv": 0.50884074,
      "roe": 0.1102,
      "div_yld": 2.23,
      "has_div": true,
      "ex_div_date": "2026-03-04",
      "de_ratio": 0.18076,
      "eps_growth": -0.19,
      "fcf_yield": 0.10500624390324026,
      "avg_volume": 2167715
    },
    "vol_20d": 0.004794287293823049,
    "avg_volume": 1187377.95,
    "buy_alerted": false,
    "sell_alerted": false,
    "fund_fetched": "2026-06-17"
  },
  "MTC.BK": {
    "score": 2,
    "signal": "BUY",
    "price": 30.75,
    "fund_score": 6.3,
    "comp_score": 6.72,
    "fund": {
      "pe": 9.346504,
      "pbv": 1.4513617,
      "roe": 0.16724001,
      "div_yld": 0.98,
      "has_div": true,
      "ex_div_date": "2026-04-28",
      "de_ratio": 3.25914,
      "eps_growth": 0.162,
      "fcf_yield": null,
      "avg_volume": 13752694
    },
    "vol_20d": 0.020303346946416178,
    "avg_volume": 11874684.45,
    "buy_alerted": false,
    "sell_alerted": false,
    "fund_fetched": "2026-06-22"
  },
  "CPF.BK": {
    "score": 1,
    "signal": "WATCH",
    "price": 19.5,
    "fund_score": 6.8,
    "comp_score": 6.32,
    "fund": {
      "pe": 7.3584905,
      "pbv": 0.6838266,
      "roe": 0.084750004,
      "div_yld": 2.59,
      "has_div": true,
      "ex_div_date": "2026-05-05",
      "de_ratio": 1.97908,
      "eps_growth": -0.435,
      "fcf_yield": 0.23077312466309832,
      "avg_volume": 29235787
    },
    "vol_20d": 0.009564744439423616,
    "avg_volume": 27305967.15,
    "buy_alerted": false,
    "sell_alerted": false,
    "fund_fetched": null
  },
  "SAWAD.BK": {
    "score": 1,
    "signal": "WATCH",
    "price": 23.100000381469727,
    "fund_score": 7.4,
    "comp_score": 6.56,
    "fund": {
      "pe": 7.287066,
      "pbv": 0.9878972,
      "roe": 0.14013,
      "div_yld": 3.32,
      "has_div": true,
      "ex_div_date": "2026-05-07",
      "de_ratio": 1.44954,
      "eps_growth": 0.227,
      "fcf_yield": null,
      "avg_volume": 16758138
    },
    "vol_20d": 0.024309639907868667,
    "avg_volume": 16597223.65,
    "buy_alerted": false,
    "sell_alerted": false,
    "fund_fetched": "2026-06-17"
  },
  "BAM.BK": {
    "score": 2,
    "signal": "BUY",
    "price": 6.5,
    "fund_score": 4.7,
    "comp_score": 6.08,
    "fund": {
      "pe": 11.607142,
      "pbv": 0.46708822,
      "roe": 0.04054,
      "div_yld": 7.69,
      "has_div": true,
      "ex_div_date": "2026-05-05",
      "de_ratio": 1.90557,
      "eps_growth": -0.001,
      "fcf_yield": null,
      "avg_volume": 12932154
    },
    "vol_20d": 0.01464356968537286,
    "avg_volume": 10909114.15,
    "buy_alerted": false,
    "sell_alerted": false,
    "fund_fetched": "2026-06-22"
  },
  "KTB.BK": {
    "score": 3,
    "signal": "BUY",
    "price": 36.5,
    "fund_score": 5.3,
    "comp_score": 6.92,
    "fund": {
      "pe": 10.428572,
      "pbv": 1.0852437,
      "roe": 0.10986,
      "div_yld": 9.97,
      "has_div": true,
      "ex_div_date": "2026-04-10",
      "de_ratio": null,
      "eps_growth": 0.06,
      "fcf_yield": null,
      "avg_volume": 73290001
    },
    "vol_20d": 0.009682718345835435,
    "avg_volume": 54089215.5,
    "buy_alerted": false,
    "sell_alerted": false,
    "fund_fetched": "2026-06-22"
  },
  "TTB.BK": {
    "score": 3,
    "signal": "BUY",
    "price": 2.4000000953674316,
    "fund_score": 5.8,
    "comp_score": 7.12,
    "fund": {
      "pe": 10.434783,
      "pbv": 0.9084028,
      "roe": 0.08541001,
      "div_yld": 5.58,
      "has_div": true,
      "ex_div_date": "2026-04-27",
      "de_ratio": null,
      "eps_growth": 0.112,
      "fcf_yield": null,
      "avg_volume": 257499578
    },
    "vol_20d": 0.01256034799281041,
    "avg_volume": 203107203.55,
    "buy_alerted": false,
    "sell_alerted": false,
    "fund_fetched": "2026-06-22"
  },
  "TISCO.BK": {
    "score": 3,
    "signal": "BUY",
    "price": 117.5,
    "fund_score": 4.7,
    "comp_score": 6.68,
    "fund": {
      "pe": 13.938315,
      "pbv": 2.1689773,
      "roe": 0.15027,
      "div_yld": 6.65,
      "has_div": true,
      "ex_div_date": "2026-04-29",
      "de_ratio": null,
      "eps_growth": 0.059,
      "fcf_yield": null,
      "avg_volume": 4073268
    },
    "vol_20d": 0.008358052746491172,
    "avg_volume": 3271090.85,
    "buy_alerted": false,
    "sell_alerted": false,
    "fund_fetched": "2026-06-22"
  },
  "AOT.BK": {
    "score": 3,
    "signal": "BUY",
    "price": 61.5,
    "fund_score": 4.7,
    "comp_score": 6.68,
    "fund": {
      "pe": 48.425198,
      "pbv": 6.7761126,
      "roe": 0.14353,
      "div_yld": 1.33,
      "has_div": true,
      "ex_div_date": "2025-12-11",
      "de_ratio": 0.34521,
      "eps_growth": 0.131,
      "fcf_yield": 0.014642359481700737,
      "avg_volume": 30163445
    },
    "vol_20d": 0.015395060436637862,
    "avg_volume": 30425897.65,
    "buy_alerted": false,
    "sell_alerted": false,
    "fund_fetched": "2026-06-22"
  },
  "THRE.BK": {
    "score": 0,
    "signal": "HOLD",
    "price": 0.3799999952316284,
    "fund_score": 4.2,
    "comp_score": 4.68,
    "fund": {
      "pe": 12.666667,
      "pbv": 0.42937854,
      "roe": 0.04113,
      "div_yld": 0.0,
      "has_div": false,
      "ex_div_date": "2021-04-29",
      "de_ratio": 0.00255,
      "eps_growth": null,
      "fcf_yield": 0.42400615251193874,
      "avg_volume": 2751359
    },
    "vol_20d": 0.019424272947324465,
    "avg_volume": 2773275.2,
    "buy_alerted": false,
    "sell_alerted": false,
    "fund_fetched": null
  },
  "BLA.BK": {
    "score": 1,
    "signal": "WATCH",
    "price": 24.0,
    "fund_score": 8.4,
    "comp_score": 6.96,
    "fund": {
      "pe": 5.5944057,
      "pbv": 0.7723499,
      "roe": 0.14529,
      "div_yld": 3.54,
      "has_div": true,
      "ex_div_date": "2026-04-21",
      "de_ratio": null,
      "eps_growth": 0.284,
      "fcf_yield": 0.1366716002338368,
      "avg_volume": 2616136
    },
    "vol_20d": 0.021005212988959025,
    "avg_volume": 3301893.9,
    "buy_alerted": false,
    "sell_alerted": false,
    "fund_fetched": "2026-06-15"
  },
  "TIDLOR.BK": {
    "score": 3,
    "signal": "BUY",
    "price": 19.399999618530273,
    "fund_score": 5.8,
    "comp_score": 7.12,
    "fund": {
      "pe": 10.486486,
      "pbv": 1.6287465,
      "roe": 0.1588,
      "div_yld": 5.42,
      "has_div": true,
      "ex_div_date": "2026-06-02",
      "de_ratio": 2.0432900000000003,
      "eps_growth": 0.355,
      "fcf_yield": null,
      "avg_volume": 30967298
    },
    "vol_20d": 0.02502227363686804,
    "avg_volume": 26133938.45,
    "buy_alerted": false,
    "sell_alerted": false,
    "fund_fetched": "2026-06-22"
  },
  "SCC.BK": {
    "score": 2,
    "signal": "BUY",
    "price": 241.0,
    "fund_score": 5.3,
    "comp_score": 6.32,
    "fund": {
      "pe": 15.0625,
      "pbv": 0.82450104,
      "roe": 0.03845,
      "div_yld": 2.07,
      "has_div": true,
      "ex_div_date": "2026-04-01",
      "de_ratio": 0.8404600000000001,
      "eps_growth": 4.663,
      "fcf_yield": -0.02669765453873037,
      "avg_volume": 5435333
    },
    "vol_20d": 0.011425423511243326,
    "avg_volume": 4498664.15,
    "buy_alerted": false,
    "sell_alerted": false,
    "fund_fetched": "2026-06-22"
  },
  "KTC.BK": {
    "score": 2,
    "signal": "BUY",
    "price": 32.25,
    "fund_score": 5.8,
    "comp_score": 6.52,
    "fund": {
      "pe": 10.2707,
      "pbv": 1.7950574,
      "roe": 0.17981,
      "div_yld": 5.53,
      "has_div": true,
      "ex_div_date": "2026-04-10",
      "de_ratio": 1.1153,
      "eps_growth": 0.167,
      "fcf_yield": null,
      "avg_volume": 15000108
    },
    "vol_20d": 0.01416452136529945,
    "avg_volume": 14002755.7,
    "buy_alerted": false,
    "sell_alerted": false,
    "fund_fetched": "2026-06-22"
  },
  "AAV.BK": {
    "score": 2,
    "signal": "BUY",
    "price": 1.100000023841858,
    "fund_score": 5.3,
    "comp_score": 6.32,
    "fund": {
      "pe": 7.857143,
      "pbv": 0.9812667,
      "roe": 0.1317,
      "div_yld": 0.0,
      "has_div": false,
      "ex_div_date": "2018-09-25",
      "de_ratio": 2.89626,
      "eps_growth": -0.394,
      "fcf_yield": 0.23756999114223704,
      "avg_volume": 69220170
    },
    "vol_20d": 0.01525378694902243,
    "avg_volume": 64963581.2,
    "buy_alerted": false,
    "sell_alerted": false,
    "fund_fetched": "2026-06-22"
  },
  "ITD.BK": {
    "score": 1,
    "signal": "WATCH",
    "price": 0.36000001430511475,
    "fund_score": 2.6,
    "comp_score": 4.64,
    "fund": {
      "pe": -0.8000001,
      "pbv": 0.6164384,
      "roe": -0.70049006,
      "div_yld": 0.0,
      "has_div": false,
      "ex_div_date": "2019-05-14",
      "de_ratio": 11.6922,
      "eps_growth": null,
      "fcf_yield": 3.9177813968723267,
      "avg_volume": 26771778
    },
    "vol_20d": 0.02727289834555523,
    "avg_volume": 13694897.05,
    "buy_alerted": false,
    "sell_alerted": false,
    "fund_fetched": "2026-06-04"
  },
  "THAI.BK": {
    "score": -2,
    "signal": "SELL",
    "price": 6.099999904632568,
    "fund_score": 6.8,
    "comp_score": 4.52,
    "fund": {
      "pe": 5.5454545,
      "pbv": 1.9501278,
      "roe": 0.43326,
      "div_yld": 3.41,
      "has_div": true,
      "ex_div_date": "2026-04-24",
      "de_ratio": 1.35294,
      "eps_growth": 0.027,
      "fcf_yield": 0.0408231052006007,
      "avg_volume": 82175194
    },
    "vol_20d": 0.028546718049678836,
    "avg_volume": 163636466.45,
    "buy_alerted": false,
    "sell_alerted": false,
    "fund_fetched": "2026-06-16"
  },
  "BAY.BK": {
    "score": 0,
    "signal": "HOLD",
    "price": 38.75,
    "fund_score": 5.8,
    "comp_score": 5.32,
    "fund": {
      "pe": 8.688341,
      "pbv": 0.673234,
      "roe": 0.08279,
      "div_yld": 3.35,
      "has_div": true,
      "ex_div_date": "2026-05-05",
      "de_ratio": null,
      "eps_growth": 0.144,
      "fcf_yield": null,
      "avg_volume": 1926064
    },
    "vol_20d": 0.032177170027062996,
    "avg_volume": 3567893.6,
    "buy_alerted": false,
    "sell_alerted": false,
    "fund_fetched": "2026-06-16"
  },
  "BA.BK": {
    "score": 3,
    "signal": "BUY",
    "price": 18.399999618530273,
    "fund_score": 7.4,
    "comp_score": 7.76,
    "fund": {
      "pe": 9.684211,
      "pbv": 2.5191677,
      "roe": 0.25753,
      "div_yld": 7.91,
      "has_div": true,
      "ex_div_date": "2026-03-11",
      "de_ratio": 1.6706899999999998,
      "eps_growth": 0.264,
      "fcf_yield": 0.06390292825481125,
      "avg_volume": 8168764
    },
    "vol_20d": 0.018556366453373514,
    "avg_volume": 9018451.4,
    "buy_alerted": false,
    "sell_alerted": false,
    "fund_fetched": "2026-06-22"
  },
  "BEM.BK": {
    "score": 3,
    "signal": "BUY",
    "price": 6.099999904632568,
    "fund_score": 3.2,
    "comp_score": 6.08,
    "fund": {
      "pe": 24.4,
      "pbv": 2.4091625,
      "roe": 0.10183,
      "div_yld": 2.52,
      "has_div": true,
      "ex_div_date": "2026-03-10",
      "de_ratio": 3.23271,
      "eps_growth": 0.0,
      "fcf_yield": -0.24897412884113276,
      "avg_volume": 33465798
    },
    "vol_20d": 0.017133202577903697,
    "avg_volume": 44151391.8,
    "buy_alerted": false,
    "sell_alerted": false,
    "fund_fetched": "2026-06-22"
  },
  "BTS.BK": {
    "score": 2,
    "signal": "BUY",
    "price": 2.059999942779541,
    "fund_score": 2.1,
    "comp_score": 5.04,
    "fund": {
      "pe": -41.199997,
      "pbv": 0.56780595,
      "roe": -0.024230001,
      "div_yld": 0.0,
      "has_div": true,
      "ex_div_date": "2023-08-07",
      "de_ratio": 1.92679,
      "eps_growth": null,
      "fcf_yield": -0.2243700667088664,
      "avg_volume": 45084512
    },
    "vol_20d": 0.011912823942042985,
    "avg_volume": 55442468.3,
    "buy_alerted": false,
    "sell_alerted": false,
    "fund_fetched": "2026-06-22"
  },
  "JMART.BK": {
    "score": 1,
    "signal": "WATCH",
    "price": 9.399999618530273,
    "fund_score": 7.9,
    "comp_score": 6.76,
    "fund": {
      "pe": 5.595238,
      "pbv": 0.76243,
      "roe": 0.00232,
      "div_yld": 2.83,
      "has_div": true,
      "ex_div_date": "2026-05-27",
      "de_ratio": 0.65108,
      "eps_growth": 0.156,
      "fcf_yield": 0.11935702076398036,
      "avg_volume": 17993370
    },
    "vol_20d": 0.027884546757694747,
    "avg_volume": 21009839.15,
    "buy_alerted": false,
    "sell_alerted": false,
    "fund_fetched": "2026-06-04"
  },
  "TQM.BK": {
    "score": 0,
    "signal": "HOLD",
    "price": 14.199999809265137,
    "fund_score": 6.8,
    "comp_score": 5.72,
    "fund": {
      "pe": 12.24138,
      "pbv": 2.7376134,
      "roe": 0.20465,
      "div_yld": 7.86,
      "has_div": true,
      "ex_div_date": "2026-03-12",
      "de_ratio": 0.47377,
      "eps_growth": -0.187,
      "fcf_yield": 0.06961296228480968,
      "avg_volume": 766828
    },
    "vol_20d": 0.011907780940539351,
    "avg_volume": 285246.95,
    "buy_alerted": false,
    "sell_alerted": false,
    "fund_fetched": "2026-06-08"
  },
  "SINGER.BK": {
    "score": 2,
    "signal": "BUY",
    "price": 9.75,
    "fund_score": 2.6,
    "comp_score": 5.24,
    "fund": {
      "pe": 31.451612,
      "pbv": 0.5921652,
      "roe": 0.02368,
      "div_yld": 0.0,
      "has_div": false,
      "ex_div_date": "2023-05-03",
      "de_ratio": 0.08613,
      "eps_growth": null,
      "fcf_yield": -0.2047172052818567,
      "avg_volume": 9644308
    },
    "vol_20d": 0.060405497765227224,
    "avg_volume": 16210026.6,
    "buy_alerted": false,
    "sell_alerted": false,
    "fund_fetched": "2026-06-22"
  },
  "CK.BK": {
    "score": 3,
    "signal": "BUY",
    "price": 19.600000381469727,
    "fund_score": 7.4,
    "comp_score": 7.76,
    "fund": {
      "pe": 9.751244,
      "pbv": 1.1452612,
      "roe": 0.12182,
      "div_yld": 2.54,
      "has_div": true,
      "ex_div_date": "2026-03-11",
      "de_ratio": 1.4504599999999999,
      "eps_growth": 0.169,
      "fcf_yield": 0.3507408499066942,
      "avg_volume": 12339389
    },
    "vol_20d": 0.031643247510474676,
    "avg_volume": 13198861.45,
    "buy_alerted": false,
    "sell_alerted": false,
    "fund_fetched": "2026-06-22"
  },
  "SC.BK": {
    "score": -1,
    "signal": "WATCH",
    "price": 1.7899999618530273,
    "fund_score": 6.8,
    "comp_score": 5.12,
    "fund": {
      "pe": 4.972222,
      "pbv": 0.30756012,
      "roe": 0.06384,
      "div_yld": 8.33,
      "has_div": true,
      "ex_div_date": "2026-05-07",
      "de_ratio": 1.30413,
      "eps_growth": 0.073,
      "fcf_yield": 0.8976038258859188,
      "avg_volume": 5395203
    },
    "vol_20d": 0.00983840639860803,
    "avg_volume": 4138369.1,
    "buy_alerted": false,
    "sell_alerted": false,
    "fund_fetched": null
  },
  "SIRI.BK": {
    "score": 2,
    "signal": "BUY",
    "price": 1.4199999570846558,
    "fund_score": 7.4,
    "comp_score": 7.16,
    "fund": {
      "pe": 5.9166665,
      "pbv": 0.54468733,
      "roe": 0.08703,
      "div_yld": 11.19,
      "has_div": true,
      "ex_div_date": "2026-03-17",
      "de_ratio": 1.55994,
      "eps_growth": 0.071,
      "fcf_yield": 0.33062307382617184,
      "avg_volume": 31949092
    },
    "vol_20d": 0.010473809447871506,
    "avg_volume": 25441959.1,
    "buy_alerted": false,
    "sell_alerted": false,
    "fund_fetched": "2026-06-22"
  },
  "LH.BK": {
    "score": 2,
    "signal": "BUY",
    "price": 3.680000066757202,
    "fund_score": 4.7,
    "comp_score": 6.08,
    "fund": {
      "pe": 12.266666,
      "pbv": 0.9257862,
      "roe": null,
      "div_yld": 6.56,
      "has_div": true,
      "ex_div_date": "2026-04-29",
      "de_ratio": 1.49477,
      "eps_growth": -0.143,
      "fcf_yield": null,
      "avg_volume": 22130624
    },
    "vol_20d": 0.009404583118424455,
    "avg_volume": 20321922.8,
    "buy_alerted": false,
    "sell_alerted": false,
    "fund_fetched": "2026-06-22"
  },
  "AP.BK": {
    "score": -1,
    "signal": "WATCH",
    "price": 7.150000095367432,
    "fund_score": 7.4,
    "comp_score": 5.36,
    "fund": {
      "pe": 5.143885,
      "pbv": 0.47880536,
      "roe": 0.09522,
      "div_yld": 7.17,
      "has_div": true,
      "ex_div_date": "2026-05-06",
      "de_ratio": 0.6934,
      "eps_growth": 0.046,
      "fcf_yield": 0.046543776431191515,
      "avg_volume": 10098243
    },
    "vol_20d": 0.014992347993781024,
    "avg_volume": 10943115.95,
    "buy_alerted": false,
    "sell_alerted": false,
    "fund_fetched": null
  },
  "ORI.BK": {
    "score": 0,
    "signal": "HOLD",
    "price": 1.6799999475479126,
    "fund_score": 6.3,
    "comp_score": 5.52,
    "fund": {
      "pe": 5.793103,
      "pbv": 0.2013664,
      "roe": 0.03557,
      "div_yld": 4.17,
      "has_div": true,
      "ex_div_date": "2026-05-11",
      "de_ratio": 1.44473,
      "eps_growth": -0.073,
      "fcf_yield": 0.4934507709259718,
      "avg_volume": 1988919
    },
    "vol_20d": 0.008847158823759868,
    "avg_volume": 1870650.85,
    "buy_alerted": false,
    "sell_alerted": false,
    "fund_fetched": null
  },
  "WHA.BK": {
    "score": 1,
    "signal": "WATCH",
    "price": 5.099999904632568,
    "fund_score": 3.7,
    "comp_score": 5.08,
    "fund": {
      "pe": 16.451612,
      "pbv": 2.0656135,
      "roe": 0.12053,
      "div_yld": 4.09,
      "has_div": true,
      "ex_div_date": "2026-05-11",
      "de_ratio": 1.17566,
      "eps_growth": -0.274,
      "fcf_yield": -0.03688841174043124,
      "avg_volume": 109628908
    },
    "vol_20d": 0.013757018928452786,
    "avg_volume": 95589522.65,
    "buy_alerted": false,
    "sell_alerted": false,
    "fund_fetched": "2026-06-02"
  },
  "TPIPP.BK": {
    "score": 0,
    "signal": "HOLD",
    "price": 1.7599999904632568,
    "fund_score": 5.3,
    "comp_score": 5.12,
    "fund": {
      "pe": 9.777778,
      "pbv": 0.40357715,
      "roe": 0.041869998,
      "div_yld": 3.98,
      "has_div": true,
      "ex_div_date": "2026-03-11",
      "de_ratio": 0.8067700000000001,
      "eps_growth": -0.774,
      "fcf_yield": -0.12928419047619047,
      "avg_volume": 4548696
    },
    "vol_20d": 0.005710450012910172,
    "avg_volume": 2129352.3,
    "buy_alerted": false,
    "sell_alerted": false,
    "fund_fetched": "2026-04-27"
  },
  "AMATA.BK": {
    "score": 1,
    "signal": "WATCH",
    "price": 26.75,
    "fund_score": 6.8,
    "comp_score": 6.32,
    "fund": {
      "pe": 8.307453,
      "pbv": 1.2252096,
      "roe": 0.15009,
      "div_yld": 4.07,
      "has_div": true,
      "ex_div_date": "2026-05-05",
      "de_ratio": 0.68491,
      "eps_growth": 0.667,
      "fcf_yield": -0.22651469114196146,
      "avg_volume": 16133936
    },
    "vol_20d": 0.017540767746090893,
    "avg_volume": 13680362.95,
    "buy_alerted": false,
    "sell_alerted": false,
    "fund_fetched": "2026-06-15"
  },
  "SHR.BK": {
    "score": 2,
    "signal": "BUY",
    "price": 1.7300000190734863,
    "fund_score": 6.3,
    "comp_score": 6.72,
    "fund": {
      "pe": 7.9844923,
      "pbv": 0.4649288,
      "roe": -0.09962,
      "div_yld": 5.81,
      "has_div": true,
      "ex_div_date": "2026-03-11",
      "de_ratio": 1.15339,
      "eps_growth": 0.507,
      "fcf_yield": null,
      "avg_volume": 3327303
    },
    "vol_20d": 0.01957490520877329,
    "avg_volume": 2216261.0,
    "buy_alerted": false,
    "sell_alerted": false,
    "fund_fetched": "2026-06-22"
  },
  "THG.BK": {
    "score": 0,
    "signal": "HOLD",
    "price": 7.199999809265137,
    "fund_score": 6.3,
    "comp_score": 5.52,
    "fund": {
      "pe": 79.99999,
      "pbv": 0.9588494,
      "roe": 0.01337,
      "div_yld": 1.93,
      "has_div": true,
      "ex_div_date": "2026-03-12",
      "de_ratio": 0.25656,
      "eps_growth": 0.036,
      "fcf_yield": 0.06657876384808224,
      "avg_volume": 1244300
    },
    "vol_20d": 0.014055386983271658,
    "avg_volume": 926324.95,
    "buy_alerted": false,
    "sell_alerted": false,
    "fund_fetched": null
  },
  "DUSIT.BK": {
    "score": 3,
    "signal": "BUY",
    "price": 10.899999618530273,
    "fund_score": 3.2,
    "comp_score": 6.08,
    "fund": {
      "pe": 6.687116,
      "pbv": 1.6972905,
      "roe": -0.023740001,
      "div_yld": 0.0,
      "has_div": false,
      "ex_div_date": "2020-04-01",
      "de_ratio": 2.19979,
      "eps_growth": 11.029,
      "fcf_yield": -0.33148088914653606,
      "avg_volume": 271540
    },
    "vol_20d": 0.019585798143892493,
    "avg_volume": 505835.55,
    "buy_alerted": false,
    "sell_alerted": false,
    "fund_fetched": "2026-06-22"
  },
  "CENTEL.BK": {
    "score": 2,
    "signal": "BUY",
    "price": 37.5,
    "fund_score": 5.8,
    "comp_score": 6.52,
    "fund": {
      "pe": 14.940239,
      "pbv": 2.034726,
      "roe": 0.14378001,
      "div_yld": 1.84,
      "has_div": true,
      "ex_div_date": "2026-05-06",
      "de_ratio": 1.24696,
      "eps_growth": 1.865,
      "fcf_yield": 0.04935913174184415,
      "avg_volume": 5545798
    },
    "vol_20d": 0.021474935577215144,
    "avg_volume": 4043744.2,
    "buy_alerted": false,
    "sell_alerted": false,
    "fund_fetched": "2026-06-22"
  },
  "NOBLE.BK": {
    "score": -1,
    "signal": "WATCH",
    "price": 1.7699999809265137,
    "fund_score": 6.8,
    "comp_score": 5.12,
    "fund": {
      "pe": 4.3170733,
      "pbv": 0.35663915,
      "roe": 0.08203,
      "div_yld": 22.13,
      "has_div": true,
      "ex_div_date": "2025-05-07",
      "de_ratio": 2.21963,
      "eps_growth": -0.436,
      "fcf_yield": 0.6908229548327556,
      "avg_volume": 555600
    },
    "vol_20d": 0.014648298352675422,
    "avg_volume": 617458.25,
    "buy_alerted": false,
    "sell_alerted": false,
    "fund_fetched": null
  },
  "SPALI.BK": {
    "score": 2,
    "signal": "BUY",
    "price": 15.600000381469727,
    "fund_score": 6.3,
    "comp_score": 6.72,
    "fund": {
      "pe": 7.464115,
      "pbv": 0.5312085,
      "roe": 0.07326,
      "div_yld": 8.97,
      "has_div": true,
      "ex_div_date": "2026-05-06",
      "de_ratio": 0.6924399999999999,
      "eps_growth": 0.028,
      "fcf_yield": 0.025135145644059196,
      "avg_volume": 4628670
    },
    "vol_20d": 0.012651620760461139,
    "avg_volume": 3884005.85,
    "buy_alerted": false,
    "sell_alerted": false,
    "fund_fetched": "2026-06-22"
  },
  "ERW.BK": {
    "score": 3,
    "signal": "BUY",
    "price": 3.0999999046325684,
    "fund_score": 3.7,
    "comp_score": 6.28,
    "fund": {
      "pe": 17.222221,
      "pbv": 1.61711,
      "roe": 0.09275,
      "div_yld": 2.29,
      "has_div": true,
      "ex_div_date": "2026-03-10",
      "de_ratio": 1.39923,
      "eps_growth": 0.086,
      "fcf_yield": -0.0021147502072572655,
      "avg_volume": 32536833
    },
    "vol_20d": 0.026163437792342092,
    "avg_volume": 24029972.3,
    "buy_alerted": false,
    "sell_alerted": false,
    "fund_fetched": "2026-06-22"
  },
  "BCH.BK": {
    "score": 2,
    "signal": "BUY",
    "price": 9.850000381469727,
    "fund_score": 4.7,
    "comp_score": 6.08,
    "fund": {
      "pe": 19.313726,
      "pbv": 1.8247501,
      "roe": 0.09446,
      "div_yld": 4.76,
      "has_div": true,
      "ex_div_date": "2026-04-29",
      "de_ratio": 0.047670000000000004,
      "eps_growth": -0.154,
      "fcf_yield": 0.033087385900965806,
      "avg_volume": 9536485
    },
    "vol_20d": 0.011211130358359484,
    "avg_volume": 9963482.15,
    "buy_alerted": false,
    "sell_alerted": false,
    "fund_fetched": "2026-06-22"
  },
  "PR9.BK": {
    "score": 2,
    "signal": "BUY",
    "price": 17.600000381469727,
    "fund_score": 4.7,
    "comp_score": 6.08,
    "fund": {
      "pe": 17.08738,
      "pbv": 2.2836385,
      "roe": 0.13791999,
      "div_yld": 2.96,
      "has_div": true,
      "ex_div_date": "2026-04-30",
      "de_ratio": 0.00252,
      "eps_growth": -0.08,
      "fcf_yield": 0.01688263927674299,
      "avg_volume": 2667908
    },
    "vol_20d": 0.014036708951305182,
    "avg_volume": 2472525.95,
    "buy_alerted": false,
    "sell_alerted": false,
    "fund_fetched": "2026-06-22"
  },
  "BDMS.BK": {
    "score": 1,
    "signal": "WATCH",
    "price": 18.399999618530273,
    "fund_score": 4.7,
    "comp_score": 5.48,
    "fund": {
      "pe": 18.585857,
      "pbv": 2.653591,
      "roe": 0.14416,
      "div_yld": 4.35,
      "has_div": true,
      "ex_div_date": "2026-03-10",
      "de_ratio": 0.12267,
      "eps_growth": -0.066,
      "fcf_yield": 0.024734541037263448,
      "avg_volume": 54787783
    },
    "vol_20d": 0.008103185215350264,
    "avg_volume": 49158456.35,
    "buy_alerted": false,
    "sell_alerted": false,
    "fund_fetched": "2026-06-17"
  },
  "NTV.BK": {
    "score": -1,
    "signal": "WATCH",
    "price": 18.600000381469727,
    "fund_score": 4.7,
    "comp_score": 4.28,
    "fund": {
      "pe": 12.156863,
      "pbv": 1.1043164,
      "roe": 0.09199,
      "div_yld": 5.59,
      "has_div": true,
      "ex_div_date": "2026-03-19",
      "de_ratio": null,
      "eps_growth": -0.424,
      "fcf_yield": 0.037743930107526885,
      "avg_volume": 32163
    },
    "vol_20d": 0.011300068152901568,
    "avg_volume": 43163.25,
    "buy_alerted": false,
    "sell_alerted": false,
    "fund_fetched": null
  },
  "VGI.BK": {
    "score": 1,
    "signal": "WATCH",
    "price": 0.9200000166893005,
    "fund_score": 4.7,
    "comp_score": 5.48,
    "fund": {
      "pe": 92.0,
      "pbv": 0.5532171,
      "roe": -0.03615,
      "div_yld": 1.44,
      "has_div": true,
      "ex_div_date": "2025-07-29",
      "de_ratio": 0.02251,
      "eps_growth": null,
      "fcf_yield": -0.011720846307500095,
      "avg_volume": 154979457
    },
    "vol_20d": 0.030157378583418912,
    "avg_volume": 231598719.3,
    "buy_alerted": false,
    "sell_alerted": false,
    "fund_fetched": "2026-06-08"
  },
  "WORK.BK": {
    "score": -1,
    "signal": "WATCH",
    "price": 3.440000057220459,
    "fund_score": 3.2,
    "comp_score": 3.68,
    "fund": {
      "pe": -114.66667,
      "pbv": 0.36897996,
      "roe": -0.01286,
      "div_yld": 0.0,
      "has_div": true,
      "ex_div_date": "2024-03-06",
      "de_ratio": 0.037919999999999995,
      "eps_growth": null,
      "fcf_yield": -0.05495551485143008,
      "avg_volume": 119968
    },
    "vol_20d": 0.008510872525448172,
    "avg_volume": 160190.85,
    "buy_alerted": false,
    "sell_alerted": false,
    "fund_fetched": "2026-06-15"
  },
  "PSH.BK": {
    "score": -4,
    "signal": "STRONG SELL",
    "price": 3.3399999141693115,
    "fund_score": 6.8,
    "comp_score": 3.32,
    "fund": {
      "pe": 18.301369,
      "pbv": 0.18462218,
      "roe": -0.011080001,
      "div_yld": 5.36,
      "has_div": true,
      "ex_div_date": "2026-03-12",
      "de_ratio": 0.3102,
      "eps_growth": 2.0,
      "fcf_yield": 0.21844590794103336,
      "avg_volume": 550278
    },
    "vol_20d": 0.006910489962601724,
    "avg_volume": 509691.4,
    "buy_alerted": false,
    "sell_alerted": false,
    "fund_fetched": null
  },
  "ANAN.BK": {
    "score": -1,
    "signal": "WATCH",
    "price": 0.33000001311302185,
    "fund_score": 3.2,
    "comp_score": 3.68,
    "fund": {
      "pe": -2.357143,
      "pbv": 0.16793893,
      "roe": 0.0173,
      "div_yld": 0.0,
      "has_div": false,
      "ex_div_date": "2020-05-11",
      "de_ratio": 0.97021,
      "eps_growth": null,
      "fcf_yield": 0.4127013394404516,
      "avg_volume": 1920492
    },
    "vol_20d": 0.023965777470021266,
    "avg_volume": 2034290.0,
    "buy_alerted": false,
    "sell_alerted": false,
    "fund_fetched": null
  },
  "JASIF.BK": {
    "score": -2,
    "signal": "SELL",
    "price": 6.449999809265137,
    "fund_score": 3.2,
    "comp_score": 3.08,
    "fund": {
      "pe": 7.884616,
      "pbv": null,
      "roe": null,
      "div_yld": 0.0,
      "has_div": true,
      "ex_div_date": null,
      "de_ratio": null,
      "eps_growth": null,
      "fcf_yield": null,
      "avg_volume": 3231323
    },
    "vol_20d": 0.006614443004055387,
    "avg_volume": 4721700.0,
    "buy_alerted": false,
    "sell_alerted": false,
    "fund_fetched": "2026-04-27"
  },
  "LALIN.BK": {
    "score": -3,
    "signal": "SELL",
    "price": 4.28000020980835,
    "fund_score": 5.3,
    "comp_score": 3.32,
    "fund": {
      "pe": 8.916667,
      "pbv": 0.41189495,
      "roe": 0.0461,
      "div_yld": 7.04,
      "has_div": true,
      "ex_div_date": "2026-03-17",
      "de_ratio": 0.64007,
      "eps_growth": -0.211,
      "fcf_yield": 0.00952134107800051,
      "avg_volume": 56538
    },
    "vol_20d": 0.0039081490765528,
    "avg_volume": 47065.05,
    "buy_alerted": false,
    "sell_alerted": false,
    "fund_fetched": null
  },
  "MEGA.BK": {
    "score": 1,
    "signal": "WATCH",
    "price": 35.25,
    "fund_score": 7.4,
    "comp_score": 6.56,
    "fund": {
      "pe": 14.936441,
      "pbv": 2.925311,
      "roe": 0.19848,
      "div_yld": 4.64,
      "has_div": true,
      "ex_div_date": "2026-03-09",
      "de_ratio": 0.06323000000000001,
      "eps_growth": 0.344,
      "fcf_yield": 0.07068420088490733,
      "avg_volume": 879145
    },
    "vol_20d": 0.01947321680159492,
    "avg_volume": 1002764.4,
    "buy_alerted": false,
    "sell_alerted": false,
    "fund_fetched": "2026-06-19"
  },
  "JMT.BK": {
    "score": 1,
    "signal": "WATCH",
    "price": 11.199999809265137,
    "fund_score": 5.8,
    "comp_score": 5.92,
    "fund": {
      "pe": 17.23077,
      "pbv": 0.5971741,
      "roe": 0.03362,
      "div_yld": 7.61,
      "has_div": true,
      "ex_div_date": "2026-03-02",
      "de_ratio": 0.31885,
      "eps_growth": -0.248,
      "fcf_yield": 0.11636865968290797,
      "avg_volume": 16871071
    },
    "vol_20d": 0.026871844321004465,
    "avg_volume": 14996726.0,
    "buy_alerted": false,
    "sell_alerted": false,
    "fund_fetched": "2026-06-04"
  },
  "GLAND.BK": {
    "score": -2,
    "signal": "SELL",
    "price": 0.7400000095367432,
    "fund_score": 5.8,
    "comp_score": 4.12,
    "fund": {
      "pe": 9.25,
      "pbv": 0.29295328,
      "roe": 0.02688,
      "div_yld": 0.0,
      "has_div": true,
      "ex_div_date": "2026-03-04",
      "de_ratio": 0.35774,
      "eps_growth": 0.063,
      "fcf_yield": 0.10517734319322865,
      "avg_volume": 0
    },
    "vol_20d": 0.0,
    "avg_volume": 0.0,
    "buy_alerted": false,
    "sell_alerted": false,
    "fund_fetched": null
  },
  "CPN.BK": {
    "score": 0,
    "signal": "HOLD",
    "price": 67.0,
    "fund_score": 6.3,
    "comp_score": 5.52,
    "fund": {
      "pe": 15.331808,
      "pbv": 2.6206682,
      "roe": 0.1676,
      "div_yld": 3.62,
      "has_div": true,
      "ex_div_date": "2026-03-09",
      "de_ratio": 0.9338500000000001,
      "eps_growth": 0.181,
      "fcf_yield": 0.11215950986398539,
      "avg_volume": 6944600
    },
    "vol_20d": 0.009464318981164179,
    "avg_volume": 5404668.1,
    "buy_alerted": false,
    "sell_alerted": false,
    "fund_fetched": "2026-06-18"
  },
  "PYLON.BK": {
    "score": 2,
    "signal": "BUY",
    "price": 3.5999999046325684,
    "fund_score": 8.4,
    "comp_score": 7.56,
    "fund": {
      "pe": 9.999999,
      "pbv": 2.247191,
      "roe": 0.24965,
      "div_yld": 6.94,
      "has_div": true,
      "ex_div_date": "2026-03-17",
      "de_ratio": 0.09258,
      "eps_growth": 3.245,
      "fcf_yield": 0.08729137812414207,
      "avg_volume": 1103478
    },
    "vol_20d": 0.018805698607629276,
    "avg_volume": 1179010.35,
    "buy_alerted": false,
    "sell_alerted": false,
    "fund_fetched": "2026-06-22"
  },
  "PLANB.BK": {
    "score": 0,
    "signal": "HOLD",
    "price": 4.679999828338623,
    "fund_score": 6.3,
    "comp_score": 5.52,
    "fund": {
      "pe": 18.0,
      "pbv": 1.6210598,
      "roe": 0.11733,
      "div_yld": 4.97,
      "has_div": true,
      "ex_div_date": "2026-04-20",
      "de_ratio": 0.26141,
      "eps_growth": 0.25,
      "fcf_yield": 0.12786527084268542,
      "avg_volume": 22808742
    },
    "vol_20d": 0.02839370273277975,
    "avg_volume": 21723986.65,
    "buy_alerted": false,
    "sell_alerted": false,
    "fund_fetched": "2026-06-17"
  },
  "SPRC.BK": {
    "score": -1,
    "signal": "WATCH",
    "price": 7.099999904632568,
    "fund_score": 8.9,
    "comp_score": 5.96,
    "fund": {
      "pe": 3.333333,
      "pbv": 0.6591162,
      "roe": 0.21345,
      "div_yld": 8.45,
      "has_div": true,
      "ex_div_date": "2026-03-05",
      "de_ratio": 0.19454000000000002,
      "eps_growth": 9.625,
      "fcf_yield": -0.016247460906263913,
      "avg_volume": 24026142
    },
    "vol_20d": 0.012880567968649566,
    "avg_volume": 16808513.65,
    "buy_alerted": false,
    "sell_alerted": false,
    "fund_fetched": "2026-06-04"
  },
  "_last_reset_date": "2026-06-22",
  "_check_count": 4,
  "_regime": {
    "regime": "BULL",
    "set_px": 1571.87,
    "ma200": 1373.16,
    "gap_pct": 14.47,
    "updated": "2026-06-22 16:29"
  },
  "_gap_alerted_date": "2026-06-22",
  "_fund_stale_alerted_date": "2026-06-22",
  "_max_hold_alerted_date": "2026-06-22",
  "FM.BK": {
    "score": 1,
    "signal": "WATCH",
    "price": 4.159999847412109,
    "fund_score": 7.9,
    "comp_score": 6.76,
    "fund": {
      "pe": 6.0289855,
      "pbv": 1.0468042,
      "roe": 0.18515,
      "div_yld": 9.43,
      "has_div": true,
      "ex_div_date": "2026-05-07",
      "de_ratio": 0.0672,
      "eps_growth": 0.071,
      "fcf_yield": 0.050497055637600374,
      "avg_volume": 1756012
    },
    "vol_20d": 0.008381453332923066,
    "avg_volume": 746010.35,
    "buy_alerted": false,
    "sell_alerted": false,
    "fund_fetched": "2026-06-04"
  },
  "ASP.BK": {
    "score": 1,
    "signal": "WATCH",
    "price": 2.140000104904175,
    "fund_score": 4.7,
    "comp_score": 5.48,
    "fund": {
      "pe": 16.46154,
      "pbv": 0.8953975,
      "roe": 0.05899,
      "div_yld": 4.17,
      "has_div": true,
      "ex_div_date": "2026-03-11",
      "de_ratio": 1.04278,
      "eps_growth": 22.0,
      "fcf_yield": null,
      "avg_volume": 776112
    },
    "vol_20d": 0.007901227386078659,
    "avg_volume": 741905.6,
    "buy_alerted": false,
    "sell_alerted": false,
    "fund_fetched": null
  },
  "JAS.BK": {
    "score": 1,
    "signal": "WATCH",
    "price": 1.1100000143051147,
    "fund_score": 2.1,
    "comp_score": 4.44,
    "fund": {
      "pe": 111.00001,
      "pbv": 1.5061059,
      "roe": -0.16506,
      "div_yld": 0.0,
      "has_div": true,
      "ex_div_date": "2023-12-13",
      "de_ratio": 0.31965,
      "eps_growth": null,
      "fcf_yield": -0.04535470837168335,
      "avg_volume": 62078410
    },
    "vol_20d": 0.04610142169382519,
    "avg_volume": 133943039.25,
    "buy_alerted": false,
    "sell_alerted": false,
    "fund_fetched": "2026-06-19"
  },
  "LHFG.BK": {
    "score": 1,
    "signal": "WATCH",
    "price": 1.1299999952316284,
    "fund_score": 6.3,
    "comp_score": 6.12,
    "fund": {
      "pe": 7.533333,
      "pbv": 0.5695565,
      "roe": 0.077199996,
      "div_yld": 7.89,
      "has_div": true,
      "ex_div_date": "2026-04-27",
      "de_ratio": null,
      "eps_growth": 0.481,
      "fcf_yield": null,
      "avg_volume": 7910591
    },
    "vol_20d": 0.007855910220043425,
    "avg_volume": 3948009.85,
    "buy_alerted": false,
    "sell_alerted": false,
    "fund_fetched": null
  },
  "MST.BK": {
    "score": 1,
    "signal": "WATCH",
    "price": 7.199999809265137,
    "fund_score": 4.7,
    "comp_score": 5.48,
    "fund": {
      "pe": 15.319149,
      "pbv": 0.78201365,
      "roe": 0.05061,
      "div_yld": 4.03,
      "has_div": true,
      "ex_div_date": "2026-03-10",
      "de_ratio": 1.24523,
      "eps_growth": 0.348,
      "fcf_yield": null,
      "avg_volume": 52738
    },
    "vol_20d": 0.003894329952458984,
    "avg_volume": 51855.0,
    "buy_alerted": false,
    "sell_alerted": false,
    "fund_fetched": "2026-06-03"
  },
  "BTSGIF.BK": {
    "score": -2,
    "signal": "SELL",
    "price": 2.440000057220459,
    "fund_score": 2.6,
    "comp_score": 2.84,
    "fund": {
      "pe": 4.692308,
      "pbv": null,
      "roe": null,
      "div_yld": 0.0,
      "has_div": false,
      "ex_div_date": null,
      "de_ratio": null,
      "eps_growth": null,
      "fcf_yield": null,
      "avg_volume": 2342033
    },
    "vol_20d": 0.01914703498716145,
    "avg_volume": 3579561.8,
    "buy_alerted": false,
    "sell_alerted": false,
    "fund_fetched": "2026-05-08"
  },
  "KGI.BK": {
    "score": 1,
    "signal": "WATCH",
    "price": 4.380000114440918,
    "fund_score": 6.3,
    "comp_score": 6.12,
    "fund": {
      "pe": 8.938776,
      "pbv": 1.0335064,
      "roe": 0.11955,
      "div_yld": 7.11,
      "has_div": true,
      "ex_div_date": "2026-04-20",
      "de_ratio": 0.67083,
      "eps_growth": 0.6,
      "fcf_yield": null,
      "avg_volume": 2226314
    },
    "vol_20d": 0.008785775210988812,
    "avg_volume": 1529392.9,
    "buy_alerted": false,
    "sell_alerted": false,
    "fund_fetched": "2026-06-08"
  },
  "_sold_dates": {
    "JASIF.BK": "2026-05-08",
    "buy_alerted": false,
    "sell_alerted": false,
    "BPP.BK": "2026-06-08",
    "CK.BK": "2026-06-08",
    "AMATA.BK": "2026-06-11",
    "TIDLOR.BK": "2026-06-11",
    "TU.BK": "2026-06-11",
    "BTSGIF.BK": "2026-06-11",
    "LH.BK": "2026-06-11",
    "GFPT.BK": "2026-06-18"
  },
  "_last_buy_date": "2026-06-17",
  "_heartbeat_sent_date": "2026-06-22",
  "_div_summary_date": "2026-06-22"
}